{"config":{"output_file":null,"full_docs":false,"pub_only":true,"reachable_only":true,"distro_crate":false,"signatures":false,"borrow_data":false},"version":"0.19.0","compilation":{"directory":"C:\\Users\\Joao_\\.cargo\\registry\\src\\github.com-1ecc6299db9ec823\\unicase_serde-0.1.0","program":"C:\\Users\\Joao_\\.rustup\\toolchains\\nightly-x86_64-pc-windows-msvc\\bin\\rls.exe","arguments":["--crate-name","unicase_serde","C:\\Users\\Joao_\\.cargo\\registry\\src\\github.com-1ecc6299db9ec823\\unicase_serde-0.1.0\\src\\lib.rs","--json=diagnostic-rendered-ansi","--crate-type","lib","--emit=dep-info,metadata","-C","embed-bitcode=no","-C","debuginfo=2","-C","metadata=735eeb33280f7a4b","-C","extra-filename=-735eeb33280f7a4b","--out-dir","c:\\Programacao\\PreciseScheduleRefactor\\backend\\target\\rls\\debug\\deps","-L","dependency=c:\\Programacao\\PreciseScheduleRefactor\\backend\\target\\rls\\debug\\deps","--extern","serde=c:\\Programacao\\PreciseScheduleRefactor\\backend\\target\\rls\\debug\\deps\\libserde-35f78ea34d16f173.rmeta","--extern","unicase=c:\\Programacao\\PreciseScheduleRefactor\\backend\\target\\rls\\debug\\deps\\libunicase-ea2ed0c3e3ba1bd6.rmeta","--cap-lints","allow","--error-format=json","--sysroot","C:\\Users\\Joao_\\.rustup/toolchains/nightly-x86_64-pc-windows-msvc"],"output":"c:\\Programacao\\PreciseScheduleRefactor\\backend\\target\\rls\\debug\\deps\\libunicase_serde-735eeb33280f7a4b.rmeta"},"prelude":{"crate_id":{"name":"unicase_serde","disambiguator":[14846232031664629042,6410997384505045095]},"crate_root":"C:\\Users\\Joao_\\.cargo\\registry\\src\\github.com-1ecc6299db9ec823\\unicase_serde-0.1.0\\src","external_crates":[{"file_name":"C:\\Users\\Joao_\\.cargo\\registry\\src\\github.com-1ecc6299db9ec823\\unicase_serde-0.1.0\\src\\lib.rs","num":1,"id":{"name":"std","disambiguator":[15440058028324314838,7136759816456376702]}},{"file_name":"C:\\Users\\Joao_\\.cargo\\registry\\src\\github.com-1ecc6299db9ec823\\unicase_serde-0.1.0\\src\\lib.rs","num":2,"id":{"name":"core","disambiguator":[13611023294341355437,10043691270023661894]}},{"file_name":"C:\\Users\\Joao_\\.cargo\\registry\\src\\github.com-1ecc6299db9ec823\\unicase_serde-0.1.0\\src\\lib.rs","num":3,"id":{"name":"compiler_builtins","disambiguator":[7491082891882765782,16585286864171082077]}},{"file_name":"C:\\Users\\Joao_\\.cargo\\registry\\src\\github.com-1ecc6299db9ec823\\unicase_serde-0.1.0\\src\\lib.rs","num":4,"id":{"name":"rustc_std_workspace_core","disambiguator":[13475896778791491548,12248248351844131012]}},{"file_name":"C:\\Users\\Joao_\\.cargo\\registry\\src\\github.com-1ecc6299db9ec823\\unicase_serde-0.1.0\\src\\lib.rs","num":5,"id":{"name":"alloc","disambiguator":[13975790540385655660,15976512376253938233]}},{"file_name":"C:\\Users\\Joao_\\.cargo\\registry\\src\\github.com-1ecc6299db9ec823\\unicase_serde-0.1.0\\src\\lib.rs","num":6,"id":{"name":"libc","disambiguator":[5499396574709479637,2750414990817935301]}},{"file_name":"C:\\Users\\Joao_\\.cargo\\registry\\src\\github.com-1ecc6299db9ec823\\unicase_serde-0.1.0\\src\\lib.rs","num":7,"id":{"name":"unwind","disambiguator":[10352395101564145454,8297257907780302002]}},{"file_name":"C:\\Users\\Joao_\\.cargo\\registry\\src\\github.com-1ecc6299db9ec823\\unicase_serde-0.1.0\\src\\lib.rs","num":8,"id":{"name":"cfg_if","disambiguator":[1357185305564916428,435405434660691681]}},{"file_name":"C:\\Users\\Joao_\\.cargo\\registry\\src\\github.com-1ecc6299db9ec823\\unicase_serde-0.1.0\\src\\lib.rs","num":9,"id":{"name":"hashbrown","disambiguator":[13061938741543316164,7340987082701557461]}},{"file_name":"C:\\Users\\Joao_\\.cargo\\registry\\src\\github.com-1ecc6299db9ec823\\unicase_serde-0.1.0\\src\\lib.rs","num":10,"id":{"name":"rustc_std_workspace_alloc","disambiguator":[9880717160104653418,4073836104819628263]}},{"file_name":"C:\\Users\\Joao_\\.cargo\\registry\\src\\github.com-1ecc6299db9ec823\\unicase_serde-0.1.0\\src\\lib.rs","num":11,"id":{"name":"rustc_demangle","disambiguator":[15567760545898281382,260942789060521312]}},{"file_name":"C:\\Users\\Joao_\\.cargo\\registry\\src\\github.com-1ecc6299db9ec823\\unicase_serde-0.1.0\\src\\lib.rs","num":12,"id":{"name":"panic_unwind","disambiguator":[11016007445267271952,18226142088256605748]}},{"file_name":"C:\\Users\\Joao_\\.cargo\\registry\\src\\github.com-1ecc6299db9ec823\\unicase_serde-0.1.0\\src\\lib.rs","num":13,"id":{"name":"serde","disambiguator":[82456114256265139,915711230256579917]}},{"file_name":"C:\\Users\\Joao_\\.cargo\\registry\\src\\github.com-1ecc6299db9ec823\\unicase_serde-0.1.0\\src\\lib.rs","num":14,"id":{"name":"unicase","disambiguator":[675107617381213834,5296355067246975455]}}],"span":{"file_name":"C:\\Users\\Joao_\\.cargo\\registry\\src\\github.com-1ecc6299db9ec823\\unicase_serde-0.1.0\\src\\lib.rs","byte_start":1,"byte_end":16429,"line_start":2,"line_end":497,"column_start":1,"column_end":2}},"imports":[{"kind":"Use","ref_id":{"krate":0,"index":14},"span":{"file_name":"C:\\Users\\Joao_\\.cargo\\registry\\src\\github.com-1ecc6299db9ec823\\unicase_serde-0.1.0\\src\\lib.rs","byte_start":8382,"byte_end":8391,"line_start":244,"line_end":244,"column_start":24,"column_end":33},"alias_span":null,"name":"serialize","value":"","parent":{"krate":0,"index":33}},{"kind":"Use","ref_id":{"krate":0,"index":60},"span":{"file_name":"C:\\Users\\Joao_\\.cargo\\registry\\src\\github.com-1ecc6299db9ec823\\unicase_serde-0.1.0\\src\\lib.rs","byte_start":11207,"byte_end":11216,"line_start":329,"line_end":329,"column_start":24,"column_end":33},"alias_span":null,"name":"serialize","value":"","parent":{"krate":0,"index":79}}],"defs":[{"kind":"Mod","id":{"krate":0,"index":0},"span":{"file_name":"C:\\Users\\Joao_\\.cargo\\registry\\src\\github.com-1ecc6299db9ec823\\unicase_serde-0.1.0\\src\\lib.rs","byte_start":1,"byte_end":16429,"line_start":2,"line_end":497,"column_start":1,"column_end":2},"name":"","qualname":"::","value":"C:\\Users\\Joao_\\.cargo\\registry\\src\\github.com-1ecc6299db9ec823\\unicase_serde-0.1.0\\src\\lib.rs","parent":null,"children":[{"krate":0,"index":1},{"krate":0,"index":2},{"krate":0,"index":3},{"krate":0,"index":4},{"krate":0,"index":5},{"krate":0,"index":51}],"decl_id":null,"docs":" [![Build Status](https://travis-ci.org/lawliet89/unicase_serde.svg)](https://travis-ci.org/lawliet89/unicase_serde)\n [![Crates.io](https://img.shields.io/crates/v/unicase_serde.svg)](https://crates.io/crates/unicase_serde)\n [![Repository](https://img.shields.io/github/tag/lawliet89/unicase_serde.svg)](https://github.com/lawliet89/unicase_serde)\n [![Documentation](https://docs.rs/unicase_serde/badge.svg)](https://docs.rs/unicase_serde)","sig":null,"attributes":[{"value":"/ [![Build Status](https://travis-ci.org/lawliet89/unicase_serde.svg)](https://travis-ci.org/lawliet89/unicase_serde)","span":{"file_name":"C:\\Users\\Joao_\\.cargo\\registry\\src\\github.com-1ecc6299db9ec823\\unicase_serde-0.1.0\\src\\lib.rs","byte_start":1,"byte_end":120,"line_start":2,"line_end":2,"column_start":1,"column_end":120}},{"value":"/ [![Crates.io](https://img.shields.io/crates/v/unicase_serde.svg)](https://crates.io/crates/unicase_serde)","span":{"file_name":"C:\\Users\\Joao_\\.cargo\\registry\\src\\github.com-1ecc6299db9ec823\\unicase_serde-0.1.0\\src\\lib.rs","byte_start":121,"byte_end":230,"line_start":3,"line_end":3,"column_start":1,"column_end":110}},{"value":"/ [![Repository](https://img.shields.io/github/tag/lawliet89/unicase_serde.svg)](https://github.com/lawliet89/unicase_serde)","span":{"file_name":"C:\\Users\\Joao_\\.cargo\\registry\\src\\github.com-1ecc6299db9ec823\\unicase_serde-0.1.0\\src\\lib.rs","byte_start":231,"byte_end":357,"line_start":4,"line_end":4,"column_start":1,"column_end":127}},{"value":"/ [![Documentation](https://docs.rs/unicase_serde/badge.svg)](https://docs.rs/unicase_serde)","span":{"file_name":"C:\\Users\\Joao_\\.cargo\\registry\\src\\github.com-1ecc6299db9ec823\\unicase_serde-0.1.0\\src\\lib.rs","byte_start":358,"byte_end":452,"line_start":5,"line_end":5,"column_start":1,"column_end":95}},{"value":"/","span":{"file_name":"C:\\Users\\Joao_\\.cargo\\registry\\src\\github.com-1ecc6299db9ec823\\unicase_serde-0.1.0\\src\\lib.rs","byte_start":453,"byte_end":456,"line_start":6,"line_end":6,"column_start":1,"column_end":4}},{"value":"/ - Documentation:  [stable](https://docs.rs/unicase_serde/) | [master branch](https://lawliet89.github.io/unicase_serde)","span":{"file_name":"C:\\Users\\Joao_\\.cargo\\registry\\src\\github.com-1ecc6299db9ec823\\unicase_serde-0.1.0\\src\\lib.rs","byte_start":457,"byte_end":580,"line_start":7,"line_end":7,"column_start":1,"column_end":124}},{"value":"/","span":{"file_name":"C:\\Users\\Joao_\\.cargo\\registry\\src\\github.com-1ecc6299db9ec823\\unicase_serde-0.1.0\\src\\lib.rs","byte_start":581,"byte_end":584,"line_start":8,"line_end":8,"column_start":1,"column_end":4}},{"value":"/ serde Serialization and Deserialization for [UniCase](https://crates.io/crates/unicase) crate","span":{"file_name":"C:\\Users\\Joao_\\.cargo\\registry\\src\\github.com-1ecc6299db9ec823\\unicase_serde-0.1.0\\src\\lib.rs","byte_start":585,"byte_end":682,"line_start":9,"line_end":9,"column_start":1,"column_end":98}},{"value":"/","span":{"file_name":"C:\\Users\\Joao_\\.cargo\\registry\\src\\github.com-1ecc6299db9ec823\\unicase_serde-0.1.0\\src\\lib.rs","byte_start":683,"byte_end":686,"line_start":10,"line_end":10,"column_start":1,"column_end":4}},{"value":"/ Support for serialization and deserialization using","span":{"file_name":"C:\\Users\\Joao_\\.cargo\\registry\\src\\github.com-1ecc6299db9ec823\\unicase_serde-0.1.0\\src\\lib.rs","byte_start":687,"byte_end":742,"line_start":11,"line_end":11,"column_start":1,"column_end":56}},{"value":"/ [serde](https://serde.rs/).","span":{"file_name":"C:\\Users\\Joao_\\.cargo\\registry\\src\\github.com-1ecc6299db9ec823\\unicase_serde-0.1.0\\src\\lib.rs","byte_start":743,"byte_end":774,"line_start":12,"line_end":12,"column_start":1,"column_end":32}},{"value":"/","span":{"file_name":"C:\\Users\\Joao_\\.cargo\\registry\\src\\github.com-1ecc6299db9ec823\\unicase_serde-0.1.0\\src\\lib.rs","byte_start":775,"byte_end":778,"line_start":13,"line_end":13,"column_start":1,"column_end":4}},{"value":"/ ## Installation","span":{"file_name":"C:\\Users\\Joao_\\.cargo\\registry\\src\\github.com-1ecc6299db9ec823\\unicase_serde-0.1.0\\src\\lib.rs","byte_start":779,"byte_end":798,"line_start":14,"line_end":14,"column_start":1,"column_end":20}},{"value":"/","span":{"file_name":"C:\\Users\\Joao_\\.cargo\\registry\\src\\github.com-1ecc6299db9ec823\\unicase_serde-0.1.0\\src\\lib.rs","byte_start":799,"byte_end":802,"line_start":15,"line_end":15,"column_start":1,"column_end":4}},{"value":"/ Add the following to Cargo.toml:","span":{"file_name":"C:\\Users\\Joao_\\.cargo\\registry\\src\\github.com-1ecc6299db9ec823\\unicase_serde-0.1.0\\src\\lib.rs","byte_start":803,"byte_end":839,"line_start":16,"line_end":16,"column_start":1,"column_end":37}},{"value":"/","span":{"file_name":"C:\\Users\\Joao_\\.cargo\\registry\\src\\github.com-1ecc6299db9ec823\\unicase_serde-0.1.0\\src\\lib.rs","byte_start":840,"byte_end":843,"line_start":17,"line_end":17,"column_start":1,"column_end":4}},{"value":"/ ```toml","span":{"file_name":"C:\\Users\\Joao_\\.cargo\\registry\\src\\github.com-1ecc6299db9ec823\\unicase_serde-0.1.0\\src\\lib.rs","byte_start":844,"byte_end":855,"line_start":18,"line_end":18,"column_start":1,"column_end":12}},{"value":"/ serde = \"1.0\"","span":{"file_name":"C:\\Users\\Joao_\\.cargo\\registry\\src\\github.com-1ecc6299db9ec823\\unicase_serde-0.1.0\\src\\lib.rs","byte_start":856,"byte_end":873,"line_start":19,"line_end":19,"column_start":1,"column_end":18}},{"value":"/ serde_derive = \"1.0\"","span":{"file_name":"C:\\Users\\Joao_\\.cargo\\registry\\src\\github.com-1ecc6299db9ec823\\unicase_serde-0.1.0\\src\\lib.rs","byte_start":874,"byte_end":898,"line_start":20,"line_end":20,"column_start":1,"column_end":25}},{"value":"/ unicase=\"2.0\"","span":{"file_name":"C:\\Users\\Joao_\\.cargo\\registry\\src\\github.com-1ecc6299db9ec823\\unicase_serde-0.1.0\\src\\lib.rs","byte_start":899,"byte_end":916,"line_start":21,"line_end":21,"column_start":1,"column_end":18}},{"value":"/ unicase_serde = \"0.1.0\"","span":{"file_name":"C:\\Users\\Joao_\\.cargo\\registry\\src\\github.com-1ecc6299db9ec823\\unicase_serde-0.1.0\\src\\lib.rs","byte_start":917,"byte_end":944,"line_start":22,"line_end":22,"column_start":1,"column_end":28}},{"value":"/ ```","span":{"file_name":"C:\\Users\\Joao_\\.cargo\\registry\\src\\github.com-1ecc6299db9ec823\\unicase_serde-0.1.0\\src\\lib.rs","byte_start":945,"byte_end":952,"line_start":23,"line_end":23,"column_start":1,"column_end":8}},{"value":"/","span":{"file_name":"C:\\Users\\Joao_\\.cargo\\registry\\src\\github.com-1ecc6299db9ec823\\unicase_serde-0.1.0\\src\\lib.rs","byte_start":953,"byte_end":956,"line_start":24,"line_end":24,"column_start":1,"column_end":4}},{"value":"/ ## Usage","span":{"file_name":"C:\\Users\\Joao_\\.cargo\\registry\\src\\github.com-1ecc6299db9ec823\\unicase_serde-0.1.0\\src\\lib.rs","byte_start":957,"byte_end":969,"line_start":25,"line_end":25,"column_start":1,"column_end":13}},{"value":"/","span":{"file_name":"C:\\Users\\Joao_\\.cargo\\registry\\src\\github.com-1ecc6299db9ec823\\unicase_serde-0.1.0\\src\\lib.rs","byte_start":970,"byte_end":973,"line_start":26,"line_end":26,"column_start":1,"column_end":4}},{"value":"/ You will have to use the serde `with` [field attribute](https://serde.rs/field-attrs.html) to","span":{"file_name":"C:\\Users\\Joao_\\.cargo\\registry\\src\\github.com-1ecc6299db9ec823\\unicase_serde-0.1.0\\src\\lib.rs","byte_start":974,"byte_end":1071,"line_start":27,"line_end":27,"column_start":1,"column_end":98}},{"value":"/ annotate any `UniCase` or `Ascii` fields with the appropriate module. See examples below.","span":{"file_name":"C:\\Users\\Joao_\\.cargo\\registry\\src\\github.com-1ecc6299db9ec823\\unicase_serde-0.1.0\\src\\lib.rs","byte_start":1072,"byte_end":1165,"line_start":28,"line_end":28,"column_start":1,"column_end":94}},{"value":"/","span":{"file_name":"C:\\Users\\Joao_\\.cargo\\registry\\src\\github.com-1ecc6299db9ec823\\unicase_serde-0.1.0\\src\\lib.rs","byte_start":1166,"byte_end":1169,"line_start":29,"line_end":29,"column_start":1,"column_end":4}},{"value":"/ ## Serialization","span":{"file_name":"C:\\Users\\Joao_\\.cargo\\registry\\src\\github.com-1ecc6299db9ec823\\unicase_serde-0.1.0\\src\\lib.rs","byte_start":1170,"byte_end":1190,"line_start":30,"line_end":30,"column_start":1,"column_end":21}},{"value":"/ Serialization for any `UniCase<S>` and `Ascii<S>` where  `S: AsRef<str>` is","span":{"file_name":"C:\\Users\\Joao_\\.cargo\\registry\\src\\github.com-1ecc6299db9ec823\\unicase_serde-0.1.0\\src\\lib.rs","byte_start":1191,"byte_end":1270,"line_start":31,"line_end":31,"column_start":1,"column_end":80}},{"value":"/ implemented. Examples for `S` include `&str`, `Cow<'a, str>`, and `String`.","span":{"file_name":"C:\\Users\\Joao_\\.cargo\\registry\\src\\github.com-1ecc6299db9ec823\\unicase_serde-0.1.0\\src\\lib.rs","byte_start":1271,"byte_end":1350,"line_start":32,"line_end":32,"column_start":1,"column_end":80}},{"value":"/","span":{"file_name":"C:\\Users\\Joao_\\.cargo\\registry\\src\\github.com-1ecc6299db9ec823\\unicase_serde-0.1.0\\src\\lib.rs","byte_start":1351,"byte_end":1354,"line_start":33,"line_end":33,"column_start":1,"column_end":4}},{"value":"/ The same `Serialize` implementation is provided in all the modules.","span":{"file_name":"C:\\Users\\Joao_\\.cargo\\registry\\src\\github.com-1ecc6299db9ec823\\unicase_serde-0.1.0\\src\\lib.rs","byte_start":1355,"byte_end":1426,"line_start":34,"line_end":34,"column_start":1,"column_end":72}},{"value":"/","span":{"file_name":"C:\\Users\\Joao_\\.cargo\\registry\\src\\github.com-1ecc6299db9ec823\\unicase_serde-0.1.0\\src\\lib.rs","byte_start":1427,"byte_end":1430,"line_start":35,"line_end":35,"column_start":1,"column_end":4}},{"value":"/ ## Deserialization","span":{"file_name":"C:\\Users\\Joao_\\.cargo\\registry\\src\\github.com-1ecc6299db9ec823\\unicase_serde-0.1.0\\src\\lib.rs","byte_start":1431,"byte_end":1453,"line_start":36,"line_end":36,"column_start":1,"column_end":23}},{"value":"/","span":{"file_name":"C:\\Users\\Joao_\\.cargo\\registry\\src\\github.com-1ecc6299db9ec823\\unicase_serde-0.1.0\\src\\lib.rs","byte_start":1454,"byte_end":1457,"line_start":37,"line_end":37,"column_start":1,"column_end":4}},{"value":"/ You can deserialize strings into `UniCase<S>` and `Ascii<S>` where","span":{"file_name":"C:\\Users\\Joao_\\.cargo\\registry\\src\\github.com-1ecc6299db9ec823\\unicase_serde-0.1.0\\src\\lib.rs","byte_start":1458,"byte_end":1528,"line_start":38,"line_end":38,"column_start":1,"column_end":71}},{"value":"/","span":{"file_name":"C:\\Users\\Joao_\\.cargo\\registry\\src\\github.com-1ecc6299db9ec823\\unicase_serde-0.1.0\\src\\lib.rs","byte_start":1529,"byte_end":1532,"line_start":39,"line_end":39,"column_start":1,"column_end":4}},{"value":"/ - `S: FromStr + AsRef<str>`","span":{"file_name":"C:\\Users\\Joao_\\.cargo\\registry\\src\\github.com-1ecc6299db9ec823\\unicase_serde-0.1.0\\src\\lib.rs","byte_start":1533,"byte_end":1564,"line_start":40,"line_end":40,"column_start":1,"column_end":32}},{"value":"/ - `S: From<&'de str> + AsRef<str> + 'de`","span":{"file_name":"C:\\Users\\Joao_\\.cargo\\registry\\src\\github.com-1ecc6299db9ec823\\unicase_serde-0.1.0\\src\\lib.rs","byte_start":1565,"byte_end":1609,"line_start":41,"line_end":41,"column_start":1,"column_end":45}},{"value":"/","span":{"file_name":"C:\\Users\\Joao_\\.cargo\\registry\\src\\github.com-1ecc6299db9ec823\\unicase_serde-0.1.0\\src\\lib.rs","byte_start":1610,"byte_end":1613,"line_start":42,"line_end":42,"column_start":1,"column_end":4}},{"value":"/ ### `S: FromStr + AsRef<str>`","span":{"file_name":"C:\\Users\\Joao_\\.cargo\\registry\\src\\github.com-1ecc6299db9ec823\\unicase_serde-0.1.0\\src\\lib.rs","byte_start":1614,"byte_end":1647,"line_start":43,"line_end":43,"column_start":1,"column_end":34}},{"value":"/ The `Deserialize` implementation is provided in the `unicase_serde::unicase` and","span":{"file_name":"C:\\Users\\Joao_\\.cargo\\registry\\src\\github.com-1ecc6299db9ec823\\unicase_serde-0.1.0\\src\\lib.rs","byte_start":1648,"byte_end":1732,"line_start":44,"line_end":44,"column_start":1,"column_end":85}},{"value":"/ `unicase_serde::ascii` modules.","span":{"file_name":"C:\\Users\\Joao_\\.cargo\\registry\\src\\github.com-1ecc6299db9ec823\\unicase_serde-0.1.0\\src\\lib.rs","byte_start":1733,"byte_end":1768,"line_start":45,"line_end":45,"column_start":1,"column_end":36}},{"value":"/ Conversion is done using the `FromStr::from_str` function.","span":{"file_name":"C:\\Users\\Joao_\\.cargo\\registry\\src\\github.com-1ecc6299db9ec823\\unicase_serde-0.1.0\\src\\lib.rs","byte_start":1769,"byte_end":1831,"line_start":46,"line_end":46,"column_start":1,"column_end":63}},{"value":"/","span":{"file_name":"C:\\Users\\Joao_\\.cargo\\registry\\src\\github.com-1ecc6299db9ec823\\unicase_serde-0.1.0\\src\\lib.rs","byte_start":1832,"byte_end":1835,"line_start":47,"line_end":47,"column_start":1,"column_end":4}},{"value":"/ Typically, you will use the this implementation for any Rust built in type that owns the data","span":{"file_name":"C:\\Users\\Joao_\\.cargo\\registry\\src\\github.com-1ecc6299db9ec823\\unicase_serde-0.1.0\\src\\lib.rs","byte_start":1836,"byte_end":1933,"line_start":48,"line_end":48,"column_start":1,"column_end":98}},{"value":"/ and does not borrow anything.","span":{"file_name":"C:\\Users\\Joao_\\.cargo\\registry\\src\\github.com-1ecc6299db9ec823\\unicase_serde-0.1.0\\src\\lib.rs","byte_start":1934,"byte_end":1967,"line_start":49,"line_end":49,"column_start":1,"column_end":34}},{"value":"/ Example include `String`.","span":{"file_name":"C:\\Users\\Joao_\\.cargo\\registry\\src\\github.com-1ecc6299db9ec823\\unicase_serde-0.1.0\\src\\lib.rs","byte_start":1968,"byte_end":1997,"line_start":50,"line_end":50,"column_start":1,"column_end":30}},{"value":"/","span":{"file_name":"C:\\Users\\Joao_\\.cargo\\registry\\src\\github.com-1ecc6299db9ec823\\unicase_serde-0.1.0\\src\\lib.rs","byte_start":1998,"byte_end":2001,"line_start":51,"line_end":51,"column_start":1,"column_end":4}},{"value":"/ You will know when you need to use the second case","span":{"file_name":"C:\\Users\\Joao_\\.cargo\\registry\\src\\github.com-1ecc6299db9ec823\\unicase_serde-0.1.0\\src\\lib.rs","byte_start":2002,"byte_end":2056,"line_start":52,"line_end":52,"column_start":1,"column_end":55}},{"value":"/ when you get trait bound errors such","span":{"file_name":"C:\\Users\\Joao_\\.cargo\\registry\\src\\github.com-1ecc6299db9ec823\\unicase_serde-0.1.0\\src\\lib.rs","byte_start":2057,"byte_end":2097,"line_start":53,"line_end":53,"column_start":1,"column_end":41}},{"value":"/ \"as the trait bound `&'a str: std::convert::From<&str>` is not satisfied\".","span":{"file_name":"C:\\Users\\Joao_\\.cargo\\registry\\src\\github.com-1ecc6299db9ec823\\unicase_serde-0.1.0\\src\\lib.rs","byte_start":2098,"byte_end":2176,"line_start":54,"line_end":54,"column_start":1,"column_end":79}},{"value":"/","span":{"file_name":"C:\\Users\\Joao_\\.cargo\\registry\\src\\github.com-1ecc6299db9ec823\\unicase_serde-0.1.0\\src\\lib.rs","byte_start":2177,"byte_end":2180,"line_start":55,"line_end":55,"column_start":1,"column_end":4}},{"value":"/ ### `S: From<&'de str> + AsRef<str> + 'de`","span":{"file_name":"C:\\Users\\Joao_\\.cargo\\registry\\src\\github.com-1ecc6299db9ec823\\unicase_serde-0.1.0\\src\\lib.rs","byte_start":2181,"byte_end":2227,"line_start":56,"line_end":56,"column_start":1,"column_end":47}},{"value":"/ The `Deserialize` implementation is provided in the `unicase_serde::unicase::borrowed` and","span":{"file_name":"C:\\Users\\Joao_\\.cargo\\registry\\src\\github.com-1ecc6299db9ec823\\unicase_serde-0.1.0\\src\\lib.rs","byte_start":2228,"byte_end":2322,"line_start":57,"line_end":57,"column_start":1,"column_end":95}},{"value":"/ `unicase_serde::ascii::borrowed` modules.","span":{"file_name":"C:\\Users\\Joao_\\.cargo\\registry\\src\\github.com-1ecc6299db9ec823\\unicase_serde-0.1.0\\src\\lib.rs","byte_start":2323,"byte_end":2368,"line_start":58,"line_end":58,"column_start":1,"column_end":46}},{"value":"/","span":{"file_name":"C:\\Users\\Joao_\\.cargo\\registry\\src\\github.com-1ecc6299db9ec823\\unicase_serde-0.1.0\\src\\lib.rs","byte_start":2369,"byte_end":2372,"line_start":59,"line_end":59,"column_start":1,"column_end":4}},{"value":"/ The second case is meant for usage with Rust built in types that borrow data. Conversion","span":{"file_name":"C:\\Users\\Joao_\\.cargo\\registry\\src\\github.com-1ecc6299db9ec823\\unicase_serde-0.1.0\\src\\lib.rs","byte_start":2373,"byte_end":2465,"line_start":60,"line_end":60,"column_start":1,"column_end":93}},{"value":"/ is done using the `Into::into` function.","span":{"file_name":"C:\\Users\\Joao_\\.cargo\\registry\\src\\github.com-1ecc6299db9ec823\\unicase_serde-0.1.0\\src\\lib.rs","byte_start":2466,"byte_end":2510,"line_start":61,"line_end":61,"column_start":1,"column_end":45}},{"value":"/","span":{"file_name":"C:\\Users\\Joao_\\.cargo\\registry\\src\\github.com-1ecc6299db9ec823\\unicase_serde-0.1.0\\src\\lib.rs","byte_start":2511,"byte_end":2514,"line_start":62,"line_end":62,"column_start":1,"column_end":4}},{"value":"/ If you use the second case with any type that owns data, you will get an error at runtime.","span":{"file_name":"C:\\Users\\Joao_\\.cargo\\registry\\src\\github.com-1ecc6299db9ec823\\unicase_serde-0.1.0\\src\\lib.rs","byte_start":2515,"byte_end":2609,"line_start":63,"line_end":63,"column_start":1,"column_end":95}},{"value":"/","span":{"file_name":"C:\\Users\\Joao_\\.cargo\\registry\\src\\github.com-1ecc6299db9ec823\\unicase_serde-0.1.0\\src\\lib.rs","byte_start":2610,"byte_end":2613,"line_start":64,"line_end":64,"column_start":1,"column_end":4}},{"value":"/ ## Example Serialization and Deserialization","span":{"file_name":"C:\\Users\\Joao_\\.cargo\\registry\\src\\github.com-1ecc6299db9ec823\\unicase_serde-0.1.0\\src\\lib.rs","byte_start":2614,"byte_end":2662,"line_start":65,"line_end":65,"column_start":1,"column_end":49}},{"value":"/ ```rust","span":{"file_name":"C:\\Users\\Joao_\\.cargo\\registry\\src\\github.com-1ecc6299db9ec823\\unicase_serde-0.1.0\\src\\lib.rs","byte_start":2663,"byte_end":2674,"line_start":66,"line_end":66,"column_start":1,"column_end":12}},{"value":"/ extern crate serde;","span":{"file_name":"C:\\Users\\Joao_\\.cargo\\registry\\src\\github.com-1ecc6299db9ec823\\unicase_serde-0.1.0\\src\\lib.rs","byte_start":2675,"byte_end":2698,"line_start":67,"line_end":67,"column_start":1,"column_end":24}},{"value":"/ #[macro_use]","span":{"file_name":"C:\\Users\\Joao_\\.cargo\\registry\\src\\github.com-1ecc6299db9ec823\\unicase_serde-0.1.0\\src\\lib.rs","byte_start":2699,"byte_end":2715,"line_start":68,"line_end":68,"column_start":1,"column_end":17}},{"value":"/ extern crate serde_derive;","span":{"file_name":"C:\\Users\\Joao_\\.cargo\\registry\\src\\github.com-1ecc6299db9ec823\\unicase_serde-0.1.0\\src\\lib.rs","byte_start":2716,"byte_end":2746,"line_start":69,"line_end":69,"column_start":1,"column_end":31}},{"value":"/ extern crate unicase;","span":{"file_name":"C:\\Users\\Joao_\\.cargo\\registry\\src\\github.com-1ecc6299db9ec823\\unicase_serde-0.1.0\\src\\lib.rs","byte_start":2747,"byte_end":2772,"line_start":70,"line_end":70,"column_start":1,"column_end":26}},{"value":"/ extern crate unicase_serde;","span":{"file_name":"C:\\Users\\Joao_\\.cargo\\registry\\src\\github.com-1ecc6299db9ec823\\unicase_serde-0.1.0\\src\\lib.rs","byte_start":2773,"byte_end":2804,"line_start":71,"line_end":71,"column_start":1,"column_end":32}},{"value":"/","span":{"file_name":"C:\\Users\\Joao_\\.cargo\\registry\\src\\github.com-1ecc6299db9ec823\\unicase_serde-0.1.0\\src\\lib.rs","byte_start":2805,"byte_end":2808,"line_start":72,"line_end":72,"column_start":1,"column_end":4}},{"value":"/ use std::borrow::Cow;","span":{"file_name":"C:\\Users\\Joao_\\.cargo\\registry\\src\\github.com-1ecc6299db9ec823\\unicase_serde-0.1.0\\src\\lib.rs","byte_start":2809,"byte_end":2834,"line_start":73,"line_end":73,"column_start":1,"column_end":26}},{"value":"/ use unicase::{UniCase, Ascii};","span":{"file_name":"C:\\Users\\Joao_\\.cargo\\registry\\src\\github.com-1ecc6299db9ec823\\unicase_serde-0.1.0\\src\\lib.rs","byte_start":2835,"byte_end":2869,"line_start":74,"line_end":74,"column_start":1,"column_end":35}},{"value":"/","span":{"file_name":"C:\\Users\\Joao_\\.cargo\\registry\\src\\github.com-1ecc6299db9ec823\\unicase_serde-0.1.0\\src\\lib.rs","byte_start":2870,"byte_end":2873,"line_start":75,"line_end":75,"column_start":1,"column_end":4}},{"value":"/ #[derive(Serialize, Deserialize)]","span":{"file_name":"C:\\Users\\Joao_\\.cargo\\registry\\src\\github.com-1ecc6299db9ec823\\unicase_serde-0.1.0\\src\\lib.rs","byte_start":2874,"byte_end":2911,"line_start":76,"line_end":76,"column_start":1,"column_end":38}},{"value":"/ struct TestUniCase<'a> {","span":{"file_name":"C:\\Users\\Joao_\\.cargo\\registry\\src\\github.com-1ecc6299db9ec823\\unicase_serde-0.1.0\\src\\lib.rs","byte_start":2912,"byte_end":2940,"line_start":77,"line_end":77,"column_start":1,"column_end":29}},{"value":"/     #[serde(with = \"unicase_serde::unicase\")]","span":{"file_name":"C:\\Users\\Joao_\\.cargo\\registry\\src\\github.com-1ecc6299db9ec823\\unicase_serde-0.1.0\\src\\lib.rs","byte_start":2941,"byte_end":2990,"line_start":78,"line_end":78,"column_start":1,"column_end":50}},{"value":"/     owned: UniCase<String>,","span":{"file_name":"C:\\Users\\Joao_\\.cargo\\registry\\src\\github.com-1ecc6299db9ec823\\unicase_serde-0.1.0\\src\\lib.rs","byte_start":2991,"byte_end":3022,"line_start":79,"line_end":79,"column_start":1,"column_end":32}},{"value":"/     #[serde(borrow, with = \"unicase_serde::unicase::borrowed\")]","span":{"file_name":"C:\\Users\\Joao_\\.cargo\\registry\\src\\github.com-1ecc6299db9ec823\\unicase_serde-0.1.0\\src\\lib.rs","byte_start":3023,"byte_end":3090,"line_start":80,"line_end":80,"column_start":1,"column_end":68}},{"value":"/     borrowed_str: UniCase<&'a str>,","span":{"file_name":"C:\\Users\\Joao_\\.cargo\\registry\\src\\github.com-1ecc6299db9ec823\\unicase_serde-0.1.0\\src\\lib.rs","byte_start":3091,"byte_end":3130,"line_start":81,"line_end":81,"column_start":1,"column_end":40}},{"value":"/     #[serde(borrow, with = \"unicase_serde::unicase::borrowed\")]","span":{"file_name":"C:\\Users\\Joao_\\.cargo\\registry\\src\\github.com-1ecc6299db9ec823\\unicase_serde-0.1.0\\src\\lib.rs","byte_start":3131,"byte_end":3198,"line_start":82,"line_end":82,"column_start":1,"column_end":68}},{"value":"/     cow_str: UniCase<Cow<'a, str>>,","span":{"file_name":"C:\\Users\\Joao_\\.cargo\\registry\\src\\github.com-1ecc6299db9ec823\\unicase_serde-0.1.0\\src\\lib.rs","byte_start":3199,"byte_end":3238,"line_start":83,"line_end":83,"column_start":1,"column_end":40}},{"value":"/ }","span":{"file_name":"C:\\Users\\Joao_\\.cargo\\registry\\src\\github.com-1ecc6299db9ec823\\unicase_serde-0.1.0\\src\\lib.rs","byte_start":3239,"byte_end":3244,"line_start":84,"line_end":84,"column_start":1,"column_end":6}},{"value":"/","span":{"file_name":"C:\\Users\\Joao_\\.cargo\\registry\\src\\github.com-1ecc6299db9ec823\\unicase_serde-0.1.0\\src\\lib.rs","byte_start":3245,"byte_end":3248,"line_start":85,"line_end":85,"column_start":1,"column_end":4}},{"value":"/ #[derive(Serialize, Deserialize)]","span":{"file_name":"C:\\Users\\Joao_\\.cargo\\registry\\src\\github.com-1ecc6299db9ec823\\unicase_serde-0.1.0\\src\\lib.rs","byte_start":3249,"byte_end":3286,"line_start":86,"line_end":86,"column_start":1,"column_end":38}},{"value":"/ struct TestAscii<'a> {","span":{"file_name":"C:\\Users\\Joao_\\.cargo\\registry\\src\\github.com-1ecc6299db9ec823\\unicase_serde-0.1.0\\src\\lib.rs","byte_start":3287,"byte_end":3313,"line_start":87,"line_end":87,"column_start":1,"column_end":27}},{"value":"/     #[serde(with = \"unicase_serde::ascii\")]","span":{"file_name":"C:\\Users\\Joao_\\.cargo\\registry\\src\\github.com-1ecc6299db9ec823\\unicase_serde-0.1.0\\src\\lib.rs","byte_start":3314,"byte_end":3361,"line_start":88,"line_end":88,"column_start":1,"column_end":48}},{"value":"/     owned: Ascii<String>,","span":{"file_name":"C:\\Users\\Joao_\\.cargo\\registry\\src\\github.com-1ecc6299db9ec823\\unicase_serde-0.1.0\\src\\lib.rs","byte_start":3362,"byte_end":3391,"line_start":89,"line_end":89,"column_start":1,"column_end":30}},{"value":"/     #[serde(borrow, with = \"unicase_serde::ascii::borrowed\")]","span":{"file_name":"C:\\Users\\Joao_\\.cargo\\registry\\src\\github.com-1ecc6299db9ec823\\unicase_serde-0.1.0\\src\\lib.rs","byte_start":3392,"byte_end":3457,"line_start":90,"line_end":90,"column_start":1,"column_end":66}},{"value":"/     borrowed_str: Ascii<&'a str>,","span":{"file_name":"C:\\Users\\Joao_\\.cargo\\registry\\src\\github.com-1ecc6299db9ec823\\unicase_serde-0.1.0\\src\\lib.rs","byte_start":3458,"byte_end":3495,"line_start":91,"line_end":91,"column_start":1,"column_end":38}},{"value":"/     #[serde(borrow, with = \"unicase_serde::ascii::borrowed\")]","span":{"file_name":"C:\\Users\\Joao_\\.cargo\\registry\\src\\github.com-1ecc6299db9ec823\\unicase_serde-0.1.0\\src\\lib.rs","byte_start":3496,"byte_end":3561,"line_start":92,"line_end":92,"column_start":1,"column_end":66}},{"value":"/     cow_str: Ascii<Cow<'a, str>>,","span":{"file_name":"C:\\Users\\Joao_\\.cargo\\registry\\src\\github.com-1ecc6299db9ec823\\unicase_serde-0.1.0\\src\\lib.rs","byte_start":3562,"byte_end":3599,"line_start":93,"line_end":93,"column_start":1,"column_end":38}},{"value":"/ }","span":{"file_name":"C:\\Users\\Joao_\\.cargo\\registry\\src\\github.com-1ecc6299db9ec823\\unicase_serde-0.1.0\\src\\lib.rs","byte_start":3600,"byte_end":3605,"line_start":94,"line_end":94,"column_start":1,"column_end":6}},{"value":"/","span":{"file_name":"C:\\Users\\Joao_\\.cargo\\registry\\src\\github.com-1ecc6299db9ec823\\unicase_serde-0.1.0\\src\\lib.rs","byte_start":3606,"byte_end":3609,"line_start":95,"line_end":95,"column_start":1,"column_end":4}},{"value":"/ # fn main() {","span":{"file_name":"C:\\Users\\Joao_\\.cargo\\registry\\src\\github.com-1ecc6299db9ec823\\unicase_serde-0.1.0\\src\\lib.rs","byte_start":3610,"byte_end":3627,"line_start":96,"line_end":96,"column_start":1,"column_end":18}},{"value":"/ # }","span":{"file_name":"C:\\Users\\Joao_\\.cargo\\registry\\src\\github.com-1ecc6299db9ec823\\unicase_serde-0.1.0\\src\\lib.rs","byte_start":3628,"byte_end":3635,"line_start":97,"line_end":97,"column_start":1,"column_end":8}},{"value":"/ ```","span":{"file_name":"C:\\Users\\Joao_\\.cargo\\registry\\src\\github.com-1ecc6299db9ec823\\unicase_serde-0.1.0\\src\\lib.rs","byte_start":3636,"byte_end":3643,"line_start":98,"line_end":98,"column_start":1,"column_end":8}},{"value":"/","span":{"file_name":"C:\\Users\\Joao_\\.cargo\\registry\\src\\github.com-1ecc6299db9ec823\\unicase_serde-0.1.0\\src\\lib.rs","byte_start":3644,"byte_end":3647,"line_start":99,"line_end":99,"column_start":1,"column_end":4}},{"value":"/ ## Example with Custom \"string\" types","span":{"file_name":"C:\\Users\\Joao_\\.cargo\\registry\\src\\github.com-1ecc6299db9ec823\\unicase_serde-0.1.0\\src\\lib.rs","byte_start":3648,"byte_end":3689,"line_start":100,"line_end":100,"column_start":1,"column_end":42}},{"value":"/ This example will demonstrate how you can use a \"custom\" string type and","span":{"file_name":"C:\\Users\\Joao_\\.cargo\\registry\\src\\github.com-1ecc6299db9ec823\\unicase_serde-0.1.0\\src\\lib.rs","byte_start":3690,"byte_end":3766,"line_start":101,"line_end":101,"column_start":1,"column_end":77}},{"value":"/ still use serialization and deserialization when wrapped inside a `UniCase` or `Ascii`. This","span":{"file_name":"C:\\Users\\Joao_\\.cargo\\registry\\src\\github.com-1ecc6299db9ec823\\unicase_serde-0.1.0\\src\\lib.rs","byte_start":3767,"byte_end":3863,"line_start":102,"line_end":102,"column_start":1,"column_end":97}},{"value":"/ is particularly useful for types like `UniCase<Cow<'a, String>>` or `UniCase<&'a String>`","span":{"file_name":"C:\\Users\\Joao_\\.cargo\\registry\\src\\github.com-1ecc6299db9ec823\\unicase_serde-0.1.0\\src\\lib.rs","byte_start":3864,"byte_end":3957,"line_start":103,"line_end":103,"column_start":1,"column_end":94}},{"value":"/ because `&String` does not implement `From::<&str>`.","span":{"file_name":"C:\\Users\\Joao_\\.cargo\\registry\\src\\github.com-1ecc6299db9ec823\\unicase_serde-0.1.0\\src\\lib.rs","byte_start":3958,"byte_end":4014,"line_start":104,"line_end":104,"column_start":1,"column_end":57}},{"value":"/","span":{"file_name":"C:\\Users\\Joao_\\.cargo\\registry\\src\\github.com-1ecc6299db9ec823\\unicase_serde-0.1.0\\src\\lib.rs","byte_start":4015,"byte_end":4018,"line_start":105,"line_end":105,"column_start":1,"column_end":4}},{"value":"/ As you can see from the example below, you can use the direct `Deserialize` implementation","span":{"file_name":"C:\\Users\\Joao_\\.cargo\\registry\\src\\github.com-1ecc6299db9ec823\\unicase_serde-0.1.0\\src\\lib.rs","byte_start":4019,"byte_end":4113,"line_start":106,"line_end":106,"column_start":1,"column_end":95}},{"value":"/ to deserialize borrowed data. This usually does not work with Rust built in types due to","span":{"file_name":"C:\\Users\\Joao_\\.cargo\\registry\\src\\github.com-1ecc6299db9ec823\\unicase_serde-0.1.0\\src\\lib.rs","byte_start":4114,"byte_end":4206,"line_start":107,"line_end":107,"column_start":1,"column_end":93}},{"value":"/ missing trait implementation. However, because the conversion is done using the","span":{"file_name":"C:\\Users\\Joao_\\.cargo\\registry\\src\\github.com-1ecc6299db9ec823\\unicase_serde-0.1.0\\src\\lib.rs","byte_start":4207,"byte_end":4290,"line_start":108,"line_end":108,"column_start":1,"column_end":84}},{"value":"/ `FromStr::from_str` function, and the function signature indicates that the `&str` passed in","span":{"file_name":"C:\\Users\\Joao_\\.cargo\\registry\\src\\github.com-1ecc6299db9ec823\\unicase_serde-0.1.0\\src\\lib.rs","byte_start":4291,"byte_end":4387,"line_start":109,"line_end":109,"column_start":1,"column_end":97}},{"value":"/ might have an ephemeral lifetime, implementors will have to convert the `&str` into an owned","span":{"file_name":"C:\\Users\\Joao_\\.cargo\\registry\\src\\github.com-1ecc6299db9ec823\\unicase_serde-0.1.0\\src\\lib.rs","byte_start":4388,"byte_end":4484,"line_start":110,"line_end":110,"column_start":1,"column_end":97}},{"value":"/ version. So you are better off using the borrowed deserializer.","span":{"file_name":"C:\\Users\\Joao_\\.cargo\\registry\\src\\github.com-1ecc6299db9ec823\\unicase_serde-0.1.0\\src\\lib.rs","byte_start":4485,"byte_end":4552,"line_start":111,"line_end":111,"column_start":1,"column_end":68}},{"value":"/","span":{"file_name":"C:\\Users\\Joao_\\.cargo\\registry\\src\\github.com-1ecc6299db9ec823\\unicase_serde-0.1.0\\src\\lib.rs","byte_start":4553,"byte_end":4556,"line_start":112,"line_end":112,"column_start":1,"column_end":4}},{"value":"/ ```rust","span":{"file_name":"C:\\Users\\Joao_\\.cargo\\registry\\src\\github.com-1ecc6299db9ec823\\unicase_serde-0.1.0\\src\\lib.rs","byte_start":4557,"byte_end":4568,"line_start":113,"line_end":113,"column_start":1,"column_end":12}},{"value":"/ extern crate serde;","span":{"file_name":"C:\\Users\\Joao_\\.cargo\\registry\\src\\github.com-1ecc6299db9ec823\\unicase_serde-0.1.0\\src\\lib.rs","byte_start":4569,"byte_end":4592,"line_start":114,"line_end":114,"column_start":1,"column_end":24}},{"value":"/ #[macro_use]","span":{"file_name":"C:\\Users\\Joao_\\.cargo\\registry\\src\\github.com-1ecc6299db9ec823\\unicase_serde-0.1.0\\src\\lib.rs","byte_start":4593,"byte_end":4609,"line_start":115,"line_end":115,"column_start":1,"column_end":17}},{"value":"/ extern crate serde_derive;","span":{"file_name":"C:\\Users\\Joao_\\.cargo\\registry\\src\\github.com-1ecc6299db9ec823\\unicase_serde-0.1.0\\src\\lib.rs","byte_start":4610,"byte_end":4640,"line_start":116,"line_end":116,"column_start":1,"column_end":31}},{"value":"/ extern crate unicase;","span":{"file_name":"C:\\Users\\Joao_\\.cargo\\registry\\src\\github.com-1ecc6299db9ec823\\unicase_serde-0.1.0\\src\\lib.rs","byte_start":4641,"byte_end":4666,"line_start":117,"line_end":117,"column_start":1,"column_end":26}},{"value":"/ extern crate unicase_serde;","span":{"file_name":"C:\\Users\\Joao_\\.cargo\\registry\\src\\github.com-1ecc6299db9ec823\\unicase_serde-0.1.0\\src\\lib.rs","byte_start":4667,"byte_end":4698,"line_start":118,"line_end":118,"column_start":1,"column_end":32}},{"value":"/","span":{"file_name":"C:\\Users\\Joao_\\.cargo\\registry\\src\\github.com-1ecc6299db9ec823\\unicase_serde-0.1.0\\src\\lib.rs","byte_start":4699,"byte_end":4702,"line_start":119,"line_end":119,"column_start":1,"column_end":4}},{"value":"/ use std::borrow::Cow;","span":{"file_name":"C:\\Users\\Joao_\\.cargo\\registry\\src\\github.com-1ecc6299db9ec823\\unicase_serde-0.1.0\\src\\lib.rs","byte_start":4703,"byte_end":4728,"line_start":120,"line_end":120,"column_start":1,"column_end":26}},{"value":"/ use std::str::FromStr;","span":{"file_name":"C:\\Users\\Joao_\\.cargo\\registry\\src\\github.com-1ecc6299db9ec823\\unicase_serde-0.1.0\\src\\lib.rs","byte_start":4729,"byte_end":4755,"line_start":121,"line_end":121,"column_start":1,"column_end":27}},{"value":"/ use unicase::UniCase;","span":{"file_name":"C:\\Users\\Joao_\\.cargo\\registry\\src\\github.com-1ecc6299db9ec823\\unicase_serde-0.1.0\\src\\lib.rs","byte_start":4756,"byte_end":4781,"line_start":122,"line_end":122,"column_start":1,"column_end":26}},{"value":"/","span":{"file_name":"C:\\Users\\Joao_\\.cargo\\registry\\src\\github.com-1ecc6299db9ec823\\unicase_serde-0.1.0\\src\\lib.rs","byte_start":4782,"byte_end":4785,"line_start":123,"line_end":123,"column_start":1,"column_end":4}},{"value":"/ #[derive(Eq, PartialEq, Debug)]","span":{"file_name":"C:\\Users\\Joao_\\.cargo\\registry\\src\\github.com-1ecc6299db9ec823\\unicase_serde-0.1.0\\src\\lib.rs","byte_start":4786,"byte_end":4821,"line_start":124,"line_end":124,"column_start":1,"column_end":36}},{"value":"/ struct CustomStr<'a>(Cow<'a, str>);","span":{"file_name":"C:\\Users\\Joao_\\.cargo\\registry\\src\\github.com-1ecc6299db9ec823\\unicase_serde-0.1.0\\src\\lib.rs","byte_start":4822,"byte_end":4861,"line_start":125,"line_end":125,"column_start":1,"column_end":40}},{"value":"/","span":{"file_name":"C:\\Users\\Joao_\\.cargo\\registry\\src\\github.com-1ecc6299db9ec823\\unicase_serde-0.1.0\\src\\lib.rs","byte_start":4862,"byte_end":4865,"line_start":126,"line_end":126,"column_start":1,"column_end":4}},{"value":"/ impl<'a> AsRef<str> for CustomStr<'a> {","span":{"file_name":"C:\\Users\\Joao_\\.cargo\\registry\\src\\github.com-1ecc6299db9ec823\\unicase_serde-0.1.0\\src\\lib.rs","byte_start":4866,"byte_end":4909,"line_start":127,"line_end":127,"column_start":1,"column_end":44}},{"value":"/     fn as_ref(&self) -> &str {","span":{"file_name":"C:\\Users\\Joao_\\.cargo\\registry\\src\\github.com-1ecc6299db9ec823\\unicase_serde-0.1.0\\src\\lib.rs","byte_start":4910,"byte_end":4944,"line_start":128,"line_end":128,"column_start":1,"column_end":35}},{"value":"/         self.0.as_ref()","span":{"file_name":"C:\\Users\\Joao_\\.cargo\\registry\\src\\github.com-1ecc6299db9ec823\\unicase_serde-0.1.0\\src\\lib.rs","byte_start":4945,"byte_end":4972,"line_start":129,"line_end":129,"column_start":1,"column_end":28}},{"value":"/     }","span":{"file_name":"C:\\Users\\Joao_\\.cargo\\registry\\src\\github.com-1ecc6299db9ec823\\unicase_serde-0.1.0\\src\\lib.rs","byte_start":4973,"byte_end":4982,"line_start":130,"line_end":130,"column_start":1,"column_end":10}},{"value":"/ }","span":{"file_name":"C:\\Users\\Joao_\\.cargo\\registry\\src\\github.com-1ecc6299db9ec823\\unicase_serde-0.1.0\\src\\lib.rs","byte_start":4983,"byte_end":4988,"line_start":131,"line_end":131,"column_start":1,"column_end":6}},{"value":"/","span":{"file_name":"C:\\Users\\Joao_\\.cargo\\registry\\src\\github.com-1ecc6299db9ec823\\unicase_serde-0.1.0\\src\\lib.rs","byte_start":4989,"byte_end":4992,"line_start":132,"line_end":132,"column_start":1,"column_end":4}},{"value":"/ impl<'a> FromStr for CustomStr<'a> {","span":{"file_name":"C:\\Users\\Joao_\\.cargo\\registry\\src\\github.com-1ecc6299db9ec823\\unicase_serde-0.1.0\\src\\lib.rs","byte_start":4993,"byte_end":5033,"line_start":133,"line_end":133,"column_start":1,"column_end":41}},{"value":"/     type Err = ();","span":{"file_name":"C:\\Users\\Joao_\\.cargo\\registry\\src\\github.com-1ecc6299db9ec823\\unicase_serde-0.1.0\\src\\lib.rs","byte_start":5034,"byte_end":5056,"line_start":134,"line_end":134,"column_start":1,"column_end":23}},{"value":"/     fn from_str(s: &str) -> Result<Self, Self::Err> {","span":{"file_name":"C:\\Users\\Joao_\\.cargo\\registry\\src\\github.com-1ecc6299db9ec823\\unicase_serde-0.1.0\\src\\lib.rs","byte_start":5057,"byte_end":5114,"line_start":135,"line_end":135,"column_start":1,"column_end":58}},{"value":"/         Ok(CustomStr(Cow::from(s.to_string())))","span":{"file_name":"C:\\Users\\Joao_\\.cargo\\registry\\src\\github.com-1ecc6299db9ec823\\unicase_serde-0.1.0\\src\\lib.rs","byte_start":5115,"byte_end":5166,"line_start":136,"line_end":136,"column_start":1,"column_end":52}},{"value":"/     }","span":{"file_name":"C:\\Users\\Joao_\\.cargo\\registry\\src\\github.com-1ecc6299db9ec823\\unicase_serde-0.1.0\\src\\lib.rs","byte_start":5167,"byte_end":5176,"line_start":137,"line_end":137,"column_start":1,"column_end":10}},{"value":"/ }","span":{"file_name":"C:\\Users\\Joao_\\.cargo\\registry\\src\\github.com-1ecc6299db9ec823\\unicase_serde-0.1.0\\src\\lib.rs","byte_start":5177,"byte_end":5182,"line_start":138,"line_end":138,"column_start":1,"column_end":6}},{"value":"/","span":{"file_name":"C:\\Users\\Joao_\\.cargo\\registry\\src\\github.com-1ecc6299db9ec823\\unicase_serde-0.1.0\\src\\lib.rs","byte_start":5183,"byte_end":5186,"line_start":139,"line_end":139,"column_start":1,"column_end":4}},{"value":"/ impl<'a> From<&'a str> for CustomStr<'a> {","span":{"file_name":"C:\\Users\\Joao_\\.cargo\\registry\\src\\github.com-1ecc6299db9ec823\\unicase_serde-0.1.0\\src\\lib.rs","byte_start":5187,"byte_end":5233,"line_start":140,"line_end":140,"column_start":1,"column_end":47}},{"value":"/     fn from(s: &'a str) -> Self {","span":{"file_name":"C:\\Users\\Joao_\\.cargo\\registry\\src\\github.com-1ecc6299db9ec823\\unicase_serde-0.1.0\\src\\lib.rs","byte_start":5234,"byte_end":5271,"line_start":141,"line_end":141,"column_start":1,"column_end":38}},{"value":"/         CustomStr(Cow::from(s))","span":{"file_name":"C:\\Users\\Joao_\\.cargo\\registry\\src\\github.com-1ecc6299db9ec823\\unicase_serde-0.1.0\\src\\lib.rs","byte_start":5272,"byte_end":5307,"line_start":142,"line_end":142,"column_start":1,"column_end":36}},{"value":"/     }","span":{"file_name":"C:\\Users\\Joao_\\.cargo\\registry\\src\\github.com-1ecc6299db9ec823\\unicase_serde-0.1.0\\src\\lib.rs","byte_start":5308,"byte_end":5317,"line_start":143,"line_end":143,"column_start":1,"column_end":10}},{"value":"/ }","span":{"file_name":"C:\\Users\\Joao_\\.cargo\\registry\\src\\github.com-1ecc6299db9ec823\\unicase_serde-0.1.0\\src\\lib.rs","byte_start":5318,"byte_end":5323,"line_start":144,"line_end":144,"column_start":1,"column_end":6}},{"value":"/","span":{"file_name":"C:\\Users\\Joao_\\.cargo\\registry\\src\\github.com-1ecc6299db9ec823\\unicase_serde-0.1.0\\src\\lib.rs","byte_start":5324,"byte_end":5327,"line_start":145,"line_end":145,"column_start":1,"column_end":4}},{"value":"/ #[derive(Eq, PartialEq, Debug)]","span":{"file_name":"C:\\Users\\Joao_\\.cargo\\registry\\src\\github.com-1ecc6299db9ec823\\unicase_serde-0.1.0\\src\\lib.rs","byte_start":5328,"byte_end":5363,"line_start":146,"line_end":146,"column_start":1,"column_end":36}},{"value":"/ struct CustomString<'a>(Cow<'a, String>);","span":{"file_name":"C:\\Users\\Joao_\\.cargo\\registry\\src\\github.com-1ecc6299db9ec823\\unicase_serde-0.1.0\\src\\lib.rs","byte_start":5364,"byte_end":5409,"line_start":147,"line_end":147,"column_start":1,"column_end":46}},{"value":"/","span":{"file_name":"C:\\Users\\Joao_\\.cargo\\registry\\src\\github.com-1ecc6299db9ec823\\unicase_serde-0.1.0\\src\\lib.rs","byte_start":5410,"byte_end":5413,"line_start":148,"line_end":148,"column_start":1,"column_end":4}},{"value":"/ impl<'a> AsRef<str> for CustomString<'a> {","span":{"file_name":"C:\\Users\\Joao_\\.cargo\\registry\\src\\github.com-1ecc6299db9ec823\\unicase_serde-0.1.0\\src\\lib.rs","byte_start":5414,"byte_end":5460,"line_start":149,"line_end":149,"column_start":1,"column_end":47}},{"value":"/     fn as_ref(&self) -> &str {","span":{"file_name":"C:\\Users\\Joao_\\.cargo\\registry\\src\\github.com-1ecc6299db9ec823\\unicase_serde-0.1.0\\src\\lib.rs","byte_start":5461,"byte_end":5495,"line_start":150,"line_end":150,"column_start":1,"column_end":35}},{"value":"/         self.0.as_ref()","span":{"file_name":"C:\\Users\\Joao_\\.cargo\\registry\\src\\github.com-1ecc6299db9ec823\\unicase_serde-0.1.0\\src\\lib.rs","byte_start":5496,"byte_end":5523,"line_start":151,"line_end":151,"column_start":1,"column_end":28}},{"value":"/     }","span":{"file_name":"C:\\Users\\Joao_\\.cargo\\registry\\src\\github.com-1ecc6299db9ec823\\unicase_serde-0.1.0\\src\\lib.rs","byte_start":5524,"byte_end":5533,"line_start":152,"line_end":152,"column_start":1,"column_end":10}},{"value":"/ }","span":{"file_name":"C:\\Users\\Joao_\\.cargo\\registry\\src\\github.com-1ecc6299db9ec823\\unicase_serde-0.1.0\\src\\lib.rs","byte_start":5534,"byte_end":5539,"line_start":153,"line_end":153,"column_start":1,"column_end":6}},{"value":"/","span":{"file_name":"C:\\Users\\Joao_\\.cargo\\registry\\src\\github.com-1ecc6299db9ec823\\unicase_serde-0.1.0\\src\\lib.rs","byte_start":5540,"byte_end":5543,"line_start":154,"line_end":154,"column_start":1,"column_end":4}},{"value":"/ impl<'a> FromStr for CustomString<'a> {","span":{"file_name":"C:\\Users\\Joao_\\.cargo\\registry\\src\\github.com-1ecc6299db9ec823\\unicase_serde-0.1.0\\src\\lib.rs","byte_start":5544,"byte_end":5587,"line_start":155,"line_end":155,"column_start":1,"column_end":44}},{"value":"/     type Err = ();","span":{"file_name":"C:\\Users\\Joao_\\.cargo\\registry\\src\\github.com-1ecc6299db9ec823\\unicase_serde-0.1.0\\src\\lib.rs","byte_start":5588,"byte_end":5610,"line_start":156,"line_end":156,"column_start":1,"column_end":23}},{"value":"/     fn from_str(s: &str) -> Result<Self, Self::Err> {","span":{"file_name":"C:\\Users\\Joao_\\.cargo\\registry\\src\\github.com-1ecc6299db9ec823\\unicase_serde-0.1.0\\src\\lib.rs","byte_start":5611,"byte_end":5668,"line_start":157,"line_end":157,"column_start":1,"column_end":58}},{"value":"/         Ok(CustomString(Cow::Owned(s.to_string())))","span":{"file_name":"C:\\Users\\Joao_\\.cargo\\registry\\src\\github.com-1ecc6299db9ec823\\unicase_serde-0.1.0\\src\\lib.rs","byte_start":5669,"byte_end":5724,"line_start":158,"line_end":158,"column_start":1,"column_end":56}},{"value":"/     }","span":{"file_name":"C:\\Users\\Joao_\\.cargo\\registry\\src\\github.com-1ecc6299db9ec823\\unicase_serde-0.1.0\\src\\lib.rs","byte_start":5725,"byte_end":5734,"line_start":159,"line_end":159,"column_start":1,"column_end":10}},{"value":"/ }","span":{"file_name":"C:\\Users\\Joao_\\.cargo\\registry\\src\\github.com-1ecc6299db9ec823\\unicase_serde-0.1.0\\src\\lib.rs","byte_start":5735,"byte_end":5740,"line_start":160,"line_end":160,"column_start":1,"column_end":6}},{"value":"/","span":{"file_name":"C:\\Users\\Joao_\\.cargo\\registry\\src\\github.com-1ecc6299db9ec823\\unicase_serde-0.1.0\\src\\lib.rs","byte_start":5741,"byte_end":5744,"line_start":161,"line_end":161,"column_start":1,"column_end":4}},{"value":"/ impl<'a> From<&'a str> for CustomString<'a> {","span":{"file_name":"C:\\Users\\Joao_\\.cargo\\registry\\src\\github.com-1ecc6299db9ec823\\unicase_serde-0.1.0\\src\\lib.rs","byte_start":5745,"byte_end":5794,"line_start":162,"line_end":162,"column_start":1,"column_end":50}},{"value":"/     fn from(s: &'a str) -> Self {","span":{"file_name":"C:\\Users\\Joao_\\.cargo\\registry\\src\\github.com-1ecc6299db9ec823\\unicase_serde-0.1.0\\src\\lib.rs","byte_start":5795,"byte_end":5832,"line_start":163,"line_end":163,"column_start":1,"column_end":38}},{"value":"/         CustomString(Cow::Owned(s.to_string()))","span":{"file_name":"C:\\Users\\Joao_\\.cargo\\registry\\src\\github.com-1ecc6299db9ec823\\unicase_serde-0.1.0\\src\\lib.rs","byte_start":5833,"byte_end":5884,"line_start":164,"line_end":164,"column_start":1,"column_end":52}},{"value":"/     }","span":{"file_name":"C:\\Users\\Joao_\\.cargo\\registry\\src\\github.com-1ecc6299db9ec823\\unicase_serde-0.1.0\\src\\lib.rs","byte_start":5885,"byte_end":5894,"line_start":165,"line_end":165,"column_start":1,"column_end":10}},{"value":"/ }","span":{"file_name":"C:\\Users\\Joao_\\.cargo\\registry\\src\\github.com-1ecc6299db9ec823\\unicase_serde-0.1.0\\src\\lib.rs","byte_start":5895,"byte_end":5900,"line_start":166,"line_end":166,"column_start":1,"column_end":6}},{"value":"/","span":{"file_name":"C:\\Users\\Joao_\\.cargo\\registry\\src\\github.com-1ecc6299db9ec823\\unicase_serde-0.1.0\\src\\lib.rs","byte_start":5901,"byte_end":5904,"line_start":167,"line_end":167,"column_start":1,"column_end":4}},{"value":"/ #[derive(Serialize, Deserialize, Eq, PartialEq, Debug)]","span":{"file_name":"C:\\Users\\Joao_\\.cargo\\registry\\src\\github.com-1ecc6299db9ec823\\unicase_serde-0.1.0\\src\\lib.rs","byte_start":5905,"byte_end":5964,"line_start":168,"line_end":168,"column_start":1,"column_end":60}},{"value":"/ struct TestCustomStruct<'a> {","span":{"file_name":"C:\\Users\\Joao_\\.cargo\\registry\\src\\github.com-1ecc6299db9ec823\\unicase_serde-0.1.0\\src\\lib.rs","byte_start":5965,"byte_end":5998,"line_start":169,"line_end":169,"column_start":1,"column_end":34}},{"value":"/     #[serde(borrow, with = \"unicase_serde::unicase::borrowed\")]","span":{"file_name":"C:\\Users\\Joao_\\.cargo\\registry\\src\\github.com-1ecc6299db9ec823\\unicase_serde-0.1.0\\src\\lib.rs","byte_start":5999,"byte_end":6066,"line_start":170,"line_end":170,"column_start":1,"column_end":68}},{"value":"/     test_str: UniCase<CustomStr<'a>>,","span":{"file_name":"C:\\Users\\Joao_\\.cargo\\registry\\src\\github.com-1ecc6299db9ec823\\unicase_serde-0.1.0\\src\\lib.rs","byte_start":6067,"byte_end":6108,"line_start":171,"line_end":171,"column_start":1,"column_end":42}},{"value":"/     #[serde(borrow, with = \"unicase_serde::unicase::borrowed\")]","span":{"file_name":"C:\\Users\\Joao_\\.cargo\\registry\\src\\github.com-1ecc6299db9ec823\\unicase_serde-0.1.0\\src\\lib.rs","byte_start":6109,"byte_end":6176,"line_start":172,"line_end":172,"column_start":1,"column_end":68}},{"value":"/     test_string: UniCase<CustomString<'a>>,","span":{"file_name":"C:\\Users\\Joao_\\.cargo\\registry\\src\\github.com-1ecc6299db9ec823\\unicase_serde-0.1.0\\src\\lib.rs","byte_start":6177,"byte_end":6224,"line_start":173,"line_end":173,"column_start":1,"column_end":48}},{"value":"/     #[serde(borrow, with = \"unicase_serde::unicase::borrowed\")]","span":{"file_name":"C:\\Users\\Joao_\\.cargo\\registry\\src\\github.com-1ecc6299db9ec823\\unicase_serde-0.1.0\\src\\lib.rs","byte_start":6225,"byte_end":6292,"line_start":174,"line_end":174,"column_start":1,"column_end":68}},{"value":"/     test_str_borrowed: UniCase<CustomStr<'a>>,","span":{"file_name":"C:\\Users\\Joao_\\.cargo\\registry\\src\\github.com-1ecc6299db9ec823\\unicase_serde-0.1.0\\src\\lib.rs","byte_start":6293,"byte_end":6343,"line_start":175,"line_end":175,"column_start":1,"column_end":51}},{"value":"/     #[serde(borrow, with = \"unicase_serde::unicase::borrowed\")]","span":{"file_name":"C:\\Users\\Joao_\\.cargo\\registry\\src\\github.com-1ecc6299db9ec823\\unicase_serde-0.1.0\\src\\lib.rs","byte_start":6344,"byte_end":6411,"line_start":176,"line_end":176,"column_start":1,"column_end":68}},{"value":"/     test_string_borrowed: UniCase<CustomString<'a>>,","span":{"file_name":"C:\\Users\\Joao_\\.cargo\\registry\\src\\github.com-1ecc6299db9ec823\\unicase_serde-0.1.0\\src\\lib.rs","byte_start":6412,"byte_end":6468,"line_start":177,"line_end":177,"column_start":1,"column_end":57}},{"value":"/ }","span":{"file_name":"C:\\Users\\Joao_\\.cargo\\registry\\src\\github.com-1ecc6299db9ec823\\unicase_serde-0.1.0\\src\\lib.rs","byte_start":6469,"byte_end":6474,"line_start":178,"line_end":178,"column_start":1,"column_end":6}},{"value":"/","span":{"file_name":"C:\\Users\\Joao_\\.cargo\\registry\\src\\github.com-1ecc6299db9ec823\\unicase_serde-0.1.0\\src\\lib.rs","byte_start":6475,"byte_end":6478,"line_start":179,"line_end":179,"column_start":1,"column_end":4}},{"value":"/ # fn main() {","span":{"file_name":"C:\\Users\\Joao_\\.cargo\\registry\\src\\github.com-1ecc6299db9ec823\\unicase_serde-0.1.0\\src\\lib.rs","byte_start":6479,"byte_end":6496,"line_start":180,"line_end":180,"column_start":1,"column_end":18}},{"value":"/ # }","span":{"file_name":"C:\\Users\\Joao_\\.cargo\\registry\\src\\github.com-1ecc6299db9ec823\\unicase_serde-0.1.0\\src\\lib.rs","byte_start":6497,"byte_end":6504,"line_start":181,"line_end":181,"column_start":1,"column_end":8}},{"value":"/ ```","span":{"file_name":"C:\\Users\\Joao_\\.cargo\\registry\\src\\github.com-1ecc6299db9ec823\\unicase_serde-0.1.0\\src\\lib.rs","byte_start":6505,"byte_end":6512,"line_start":182,"line_end":182,"column_start":1,"column_end":8}}]},{"kind":"Mod","id":{"krate":0,"index":5},"span":{"file_name":"C:\\Users\\Joao_\\.cargo\\registry\\src\\github.com-1ecc6299db9ec823\\unicase_serde-0.1.0\\src\\lib.rs","byte_start":6683,"byte_end":6690,"line_start":192,"line_end":192,"column_start":9,"column_end":16},"name":"unicase","qualname":"::unicase","value":"C:\\Users\\Joao_\\.cargo\\registry\\src\\github.com-1ecc6299db9ec823\\unicase_serde-0.1.0\\src\\lib.rs","parent":null,"children":[{"krate":0,"index":6},{"krate":0,"index":7},{"krate":0,"index":99},{"krate":0,"index":8},{"krate":0,"index":9},{"krate":0,"index":10},{"krate":0,"index":11},{"krate":0,"index":12},{"krate":0,"index":13},{"krate":0,"index":14},{"krate":0,"index":17},{"krate":0,"index":33}],"decl_id":null,"docs":" Serialization and Deserialization Implementation for `UniCase` that owns data","sig":null,"attributes":[{"value":"/ Serialization and Deserialization Implementation for `UniCase` that owns data","span":{"file_name":"C:\\Users\\Joao_\\.cargo\\registry\\src\\github.com-1ecc6299db9ec823\\unicase_serde-0.1.0\\src\\lib.rs","byte_start":6697,"byte_end":6778,"line_start":193,"line_end":193,"column_start":5,"column_end":86}},{"value":"/","span":{"file_name":"C:\\Users\\Joao_\\.cargo\\registry\\src\\github.com-1ecc6299db9ec823\\unicase_serde-0.1.0\\src\\lib.rs","byte_start":6783,"byte_end":6786,"line_start":194,"line_end":194,"column_start":5,"column_end":8}},{"value":"/ See crate level documentation for details.","span":{"file_name":"C:\\Users\\Joao_\\.cargo\\registry\\src\\github.com-1ecc6299db9ec823\\unicase_serde-0.1.0\\src\\lib.rs","byte_start":6791,"byte_end":6837,"line_start":195,"line_end":195,"column_start":5,"column_end":51}}]},{"kind":"Function","id":{"krate":0,"index":14},"span":{"file_name":"C:\\Users\\Joao_\\.cargo\\registry\\src\\github.com-1ecc6299db9ec823\\unicase_serde-0.1.0\\src\\lib.rs","byte_start":7078,"byte_end":7087,"line_start":205,"line_end":205,"column_start":12,"column_end":21},"name":"serialize","qualname":"::unicase::serialize","value":"pub fn serialize<S, Ser>(&UniCase<S>, Ser) -> Result<Ser::Ok, Ser::Error>\nwhere S: AsRef<str>, Ser: Serializer","parent":null,"children":[],"decl_id":null,"docs":" Straightforward Serialization for UniCase\n","sig":null,"attributes":[{"value":"/ Straightforward Serialization for UniCase","span":{"file_name":"C:\\Users\\Joao_\\.cargo\\registry\\src\\github.com-1ecc6299db9ec823\\unicase_serde-0.1.0\\src\\lib.rs","byte_start":7021,"byte_end":7066,"line_start":204,"line_end":204,"column_start":5,"column_end":50}}]},{"kind":"Function","id":{"krate":0,"index":17},"span":{"file_name":"C:\\Users\\Joao_\\.cargo\\registry\\src\\github.com-1ecc6299db9ec823\\unicase_serde-0.1.0\\src\\lib.rs","byte_start":7368,"byte_end":7379,"line_start":214,"line_end":214,"column_start":12,"column_end":23},"name":"deserialize","qualname":"::unicase::deserialize","value":"pub fn deserialize<'de, S, D>(D) -> Result<UniCase<S>, D::Error> where\nS: FromStr + AsRef<str>, D: Deserializer","parent":null,"children":[],"decl_id":null,"docs":" Deserialization for `UniCase<S>` where `S: FromStr + AsRef<str>`\n","sig":null,"attributes":[{"value":"/ Deserialization for `UniCase<S>` where `S: FromStr + AsRef<str>`","span":{"file_name":"C:\\Users\\Joao_\\.cargo\\registry\\src\\github.com-1ecc6299db9ec823\\unicase_serde-0.1.0\\src\\lib.rs","byte_start":7288,"byte_end":7356,"line_start":213,"line_end":213,"column_start":5,"column_end":73}}]},{"kind":"Mod","id":{"krate":0,"index":33},"span":{"file_name":"C:\\Users\\Joao_\\.cargo\\registry\\src\\github.com-1ecc6299db9ec823\\unicase_serde-0.1.0\\src\\lib.rs","byte_start":8166,"byte_end":8174,"line_start":239,"line_end":239,"column_start":13,"column_end":21},"name":"borrowed","qualname":"::unicase::borrowed","value":"C:\\Users\\Joao_\\.cargo\\registry\\src\\github.com-1ecc6299db9ec823\\unicase_serde-0.1.0\\src\\lib.rs","parent":null,"children":[{"krate":0,"index":34},{"krate":0,"index":35},{"krate":0,"index":36}],"decl_id":null,"docs":" Serialization and Deserialization Implementation for `UniCase` that borrow data.","sig":null,"attributes":[{"value":"/ Serialization and Deserialization Implementation for `UniCase` that borrow data.","span":{"file_name":"C:\\Users\\Joao_\\.cargo\\registry\\src\\github.com-1ecc6299db9ec823\\unicase_serde-0.1.0\\src\\lib.rs","byte_start":8185,"byte_end":8269,"line_start":240,"line_end":240,"column_start":9,"column_end":93}},{"value":"/","span":{"file_name":"C:\\Users\\Joao_\\.cargo\\registry\\src\\github.com-1ecc6299db9ec823\\unicase_serde-0.1.0\\src\\lib.rs","byte_start":8278,"byte_end":8281,"line_start":241,"line_end":241,"column_start":9,"column_end":12}},{"value":"/ See crate level documentation for details.","span":{"file_name":"C:\\Users\\Joao_\\.cargo\\registry\\src\\github.com-1ecc6299db9ec823\\unicase_serde-0.1.0\\src\\lib.rs","byte_start":8290,"byte_end":8336,"line_start":242,"line_end":242,"column_start":9,"column_end":55}}]},{"kind":"Function","id":{"krate":0,"index":36},"span":{"file_name":"C:\\Users\\Joao_\\.cargo\\registry\\src\\github.com-1ecc6299db9ec823\\unicase_serde-0.1.0\\src\\lib.rs","byte_start":8659,"byte_end":8670,"line_start":250,"line_end":250,"column_start":16,"column_end":27},"name":"deserialize","qualname":"::unicase::borrowed::deserialize","value":"pub fn deserialize<'de, S, D>(D) -> Result<UniCase<S>, D::Error> where\nS: From<&'de str> + AsRef<str> + 'de, D: Deserializer","parent":null,"children":[],"decl_id":null,"docs":" Borrowed Deserializer for `UniCase`.","sig":null,"attributes":[{"value":"/ Borrowed Deserializer for `UniCase`.","span":{"file_name":"C:\\Users\\Joao_\\.cargo\\registry\\src\\github.com-1ecc6299db9ec823\\unicase_serde-0.1.0\\src\\lib.rs","byte_start":8402,"byte_end":8442,"line_start":246,"line_end":246,"column_start":9,"column_end":49}},{"value":"/","span":{"file_name":"C:\\Users\\Joao_\\.cargo\\registry\\src\\github.com-1ecc6299db9ec823\\unicase_serde-0.1.0\\src\\lib.rs","byte_start":8451,"byte_end":8454,"line_start":247,"line_end":247,"column_start":9,"column_end":12}},{"value":"/ Typically, you will use this for any types that borrow data. Example include `&str`.","span":{"file_name":"C:\\Users\\Joao_\\.cargo\\registry\\src\\github.com-1ecc6299db9ec823\\unicase_serde-0.1.0\\src\\lib.rs","byte_start":8463,"byte_end":8551,"line_start":248,"line_end":248,"column_start":9,"column_end":97}},{"value":"/ If you use this with any type that owns data, you will get an error at runtime.","span":{"file_name":"C:\\Users\\Joao_\\.cargo\\registry\\src\\github.com-1ecc6299db9ec823\\unicase_serde-0.1.0\\src\\lib.rs","byte_start":8560,"byte_end":8643,"line_start":249,"line_end":249,"column_start":9,"column_end":92}}]},{"kind":"Mod","id":{"krate":0,"index":51},"span":{"file_name":"C:\\Users\\Joao_\\.cargo\\registry\\src\\github.com-1ecc6299db9ec823\\unicase_serde-0.1.0\\src\\lib.rs","byte_start":9528,"byte_end":9533,"line_start":277,"line_end":277,"column_start":9,"column_end":14},"name":"ascii","qualname":"::ascii","value":"C:\\Users\\Joao_\\.cargo\\registry\\src\\github.com-1ecc6299db9ec823\\unicase_serde-0.1.0\\src\\lib.rs","parent":null,"children":[{"krate":0,"index":52},{"krate":0,"index":53},{"krate":0,"index":115},{"krate":0,"index":54},{"krate":0,"index":55},{"krate":0,"index":56},{"krate":0,"index":57},{"krate":0,"index":58},{"krate":0,"index":59},{"krate":0,"index":60},{"krate":0,"index":63},{"krate":0,"index":79}],"decl_id":null,"docs":" Serialization and Deserialization Implementation for `Ascii` that owns data","sig":null,"attributes":[{"value":"/ Serialization and Deserialization Implementation for `Ascii` that owns data","span":{"file_name":"C:\\Users\\Joao_\\.cargo\\registry\\src\\github.com-1ecc6299db9ec823\\unicase_serde-0.1.0\\src\\lib.rs","byte_start":9540,"byte_end":9619,"line_start":278,"line_end":278,"column_start":5,"column_end":84}},{"value":"/","span":{"file_name":"C:\\Users\\Joao_\\.cargo\\registry\\src\\github.com-1ecc6299db9ec823\\unicase_serde-0.1.0\\src\\lib.rs","byte_start":9624,"byte_end":9627,"line_start":279,"line_end":279,"column_start":5,"column_end":8}},{"value":"/ See crate level documentation for details.","span":{"file_name":"C:\\Users\\Joao_\\.cargo\\registry\\src\\github.com-1ecc6299db9ec823\\unicase_serde-0.1.0\\src\\lib.rs","byte_start":9632,"byte_end":9678,"line_start":280,"line_end":280,"column_start":5,"column_end":51}}]},{"kind":"Function","id":{"krate":0,"index":60},"span":{"file_name":"C:\\Users\\Joao_\\.cargo\\registry\\src\\github.com-1ecc6299db9ec823\\unicase_serde-0.1.0\\src\\lib.rs","byte_start":9917,"byte_end":9926,"line_start":290,"line_end":290,"column_start":12,"column_end":21},"name":"serialize","qualname":"::ascii::serialize","value":"pub fn serialize<S, Ser>(&Ascii<S>, Ser) -> Result<Ser::Ok, Ser::Error> where\nS: AsRef<str>, Ser: Serializer","parent":null,"children":[],"decl_id":null,"docs":" Straightforward Serialization for UniCase\n","sig":null,"attributes":[{"value":"/ Straightforward Serialization for UniCase","span":{"file_name":"C:\\Users\\Joao_\\.cargo\\registry\\src\\github.com-1ecc6299db9ec823\\unicase_serde-0.1.0\\src\\lib.rs","byte_start":9860,"byte_end":9905,"line_start":289,"line_end":289,"column_start":5,"column_end":50}}]},{"kind":"Function","id":{"krate":0,"index":63},"span":{"file_name":"C:\\Users\\Joao_\\.cargo\\registry\\src\\github.com-1ecc6299db9ec823\\unicase_serde-0.1.0\\src\\lib.rs","byte_start":10205,"byte_end":10216,"line_start":299,"line_end":299,"column_start":12,"column_end":23},"name":"deserialize","qualname":"::ascii::deserialize","value":"pub fn deserialize<'de, S, D>(D) -> Result<Ascii<S>, D::Error> where\nS: FromStr + AsRef<str>, D: Deserializer","parent":null,"children":[],"decl_id":null,"docs":" Deserialization for `UniCase<S>` where `S: FromStr + AsRef<str>`\n","sig":null,"attributes":[{"value":"/ Deserialization for `UniCase<S>` where `S: FromStr + AsRef<str>`","span":{"file_name":"C:\\Users\\Joao_\\.cargo\\registry\\src\\github.com-1ecc6299db9ec823\\unicase_serde-0.1.0\\src\\lib.rs","byte_start":10125,"byte_end":10193,"line_start":298,"line_end":298,"column_start":5,"column_end":73}}]},{"kind":"Mod","id":{"krate":0,"index":79},"span":{"file_name":"C:\\Users\\Joao_\\.cargo\\registry\\src\\github.com-1ecc6299db9ec823\\unicase_serde-0.1.0\\src\\lib.rs","byte_start":10993,"byte_end":11001,"line_start":324,"line_end":324,"column_start":13,"column_end":21},"name":"borrowed","qualname":"::ascii::borrowed","value":"C:\\Users\\Joao_\\.cargo\\registry\\src\\github.com-1ecc6299db9ec823\\unicase_serde-0.1.0\\src\\lib.rs","parent":null,"children":[{"krate":0,"index":80},{"krate":0,"index":81},{"krate":0,"index":82}],"decl_id":null,"docs":" Serialization and Deserialization Implementation for `Ascii` that borrows data","sig":null,"attributes":[{"value":"/ Serialization and Deserialization Implementation for `Ascii` that borrows data","span":{"file_name":"C:\\Users\\Joao_\\.cargo\\registry\\src\\github.com-1ecc6299db9ec823\\unicase_serde-0.1.0\\src\\lib.rs","byte_start":11012,"byte_end":11094,"line_start":325,"line_end":325,"column_start":9,"column_end":91}},{"value":"/","span":{"file_name":"C:\\Users\\Joao_\\.cargo\\registry\\src\\github.com-1ecc6299db9ec823\\unicase_serde-0.1.0\\src\\lib.rs","byte_start":11103,"byte_end":11106,"line_start":326,"line_end":326,"column_start":9,"column_end":12}},{"value":"/ See crate level documentation for details.","span":{"file_name":"C:\\Users\\Joao_\\.cargo\\registry\\src\\github.com-1ecc6299db9ec823\\unicase_serde-0.1.0\\src\\lib.rs","byte_start":11115,"byte_end":11161,"line_start":327,"line_end":327,"column_start":9,"column_end":55}}]},{"kind":"Function","id":{"krate":0,"index":82},"span":{"file_name":"C:\\Users\\Joao_\\.cargo\\registry\\src\\github.com-1ecc6299db9ec823\\unicase_serde-0.1.0\\src\\lib.rs","byte_start":11482,"byte_end":11493,"line_start":335,"line_end":335,"column_start":16,"column_end":27},"name":"deserialize","qualname":"::ascii::borrowed::deserialize","value":"pub fn deserialize<'de, S, D>(D) -> Result<Ascii<S>, D::Error> where\nS: From<&'de str> + AsRef<str> + 'de, D: Deserializer","parent":null,"children":[],"decl_id":null,"docs":" Borrowed Deserializer for `Ascii`.","sig":null,"attributes":[{"value":"/ Borrowed Deserializer for `Ascii`.","span":{"file_name":"C:\\Users\\Joao_\\.cargo\\registry\\src\\github.com-1ecc6299db9ec823\\unicase_serde-0.1.0\\src\\lib.rs","byte_start":11227,"byte_end":11265,"line_start":331,"line_end":331,"column_start":9,"column_end":47}},{"value":"/","span":{"file_name":"C:\\Users\\Joao_\\.cargo\\registry\\src\\github.com-1ecc6299db9ec823\\unicase_serde-0.1.0\\src\\lib.rs","byte_start":11274,"byte_end":11277,"line_start":332,"line_end":332,"column_start":9,"column_end":12}},{"value":"/ Typically, you will use this for any types that borrow data. Example include `&str`.","span":{"file_name":"C:\\Users\\Joao_\\.cargo\\registry\\src\\github.com-1ecc6299db9ec823\\unicase_serde-0.1.0\\src\\lib.rs","byte_start":11286,"byte_end":11374,"line_start":333,"line_end":333,"column_start":9,"column_end":97}},{"value":"/ If you use this with any type that owns data, you will get an error at runtime.","span":{"file_name":"C:\\Users\\Joao_\\.cargo\\registry\\src\\github.com-1ecc6299db9ec823\\unicase_serde-0.1.0\\src\\lib.rs","byte_start":11383,"byte_end":11466,"line_start":334,"line_end":334,"column_start":9,"column_end":92}}]}],"impls":[{"id":0,"kind":"Direct","span":{"file_name":"C:\\Users\\Joao_\\.cargo\\registry\\src\\github.com-1ecc6299db9ec823\\unicase_serde-0.1.0\\src\\lib.rs","byte_start":7634,"byte_end":7648,"line_start":221,"line_end":221,"column_start":65,"column_end":79},"value":"","parent":null,"children":[{"krate":0,"index":28},{"krate":0,"index":29},{"krate":0,"index":30}],"docs":"","sig":null,"attributes":[]},{"id":1,"kind":"Direct","span":{"file_name":"C:\\Users\\Joao_\\.cargo\\registry\\src\\github.com-1ecc6299db9ec823\\unicase_serde-0.1.0\\src\\lib.rs","byte_start":8969,"byte_end":8983,"line_start":257,"line_end":257,"column_start":76,"column_end":90},"value":"","parent":null,"children":[{"krate":0,"index":47},{"krate":0,"index":48},{"krate":0,"index":49}],"docs":"","sig":null,"attributes":[]},{"id":2,"kind":"Direct","span":{"file_name":"C:\\Users\\Joao_\\.cargo\\registry\\src\\github.com-1ecc6299db9ec823\\unicase_serde-0.1.0\\src\\lib.rs","byte_start":10467,"byte_end":10479,"line_start":306,"line_end":306,"column_start":65,"column_end":77},"value":"","parent":null,"children":[{"krate":0,"index":74},{"krate":0,"index":75},{"krate":0,"index":76}],"docs":"","sig":null,"attributes":[]},{"id":3,"kind":"Direct","span":{"file_name":"C:\\Users\\Joao_\\.cargo\\registry\\src\\github.com-1ecc6299db9ec823\\unicase_serde-0.1.0\\src\\lib.rs","byte_start":11788,"byte_end":11800,"line_start":342,"line_end":342,"column_start":76,"column_end":88},"value":"","parent":null,"children":[{"krate":0,"index":93},{"krate":0,"index":94},{"krate":0,"index":95}],"docs":"","sig":null,"attributes":[]}],"refs":[],"macro_refs":[],"relations":[{"span":{"file_name":"C:\\Users\\Joao_\\.cargo\\registry\\src\\github.com-1ecc6299db9ec823\\unicase_serde-0.1.0\\src\\lib.rs","byte_start":7634,"byte_end":7648,"line_start":221,"line_end":221,"column_start":65,"column_end":79},"kind":{"Impl":{"id":0}},"from":{"krate":0,"index":21},"to":{"krate":13,"index":1276}},{"span":{"file_name":"C:\\Users\\Joao_\\.cargo\\registry\\src\\github.com-1ecc6299db9ec823\\unicase_serde-0.1.0\\src\\lib.rs","byte_start":8969,"byte_end":8983,"line_start":257,"line_end":257,"column_start":76,"column_end":90},"kind":{"Impl":{"id":1}},"from":{"krate":0,"index":40},"to":{"krate":13,"index":1276}},{"span":{"file_name":"C:\\Users\\Joao_\\.cargo\\registry\\src\\github.com-1ecc6299db9ec823\\unicase_serde-0.1.0\\src\\lib.rs","byte_start":10467,"byte_end":10479,"line_start":306,"line_end":306,"column_start":65,"column_end":77},"kind":{"Impl":{"id":2}},"from":{"krate":0,"index":67},"to":{"krate":13,"index":1276}},{"span":{"file_name":"C:\\Users\\Joao_\\.cargo\\registry\\src\\github.com-1ecc6299db9ec823\\unicase_serde-0.1.0\\src\\lib.rs","byte_start":11788,"byte_end":11800,"line_start":342,"line_end":342,"column_start":76,"column_end":88},"kind":{"Impl":{"id":3}},"from":{"krate":0,"index":86},"to":{"krate":13,"index":1276}}]}